Workbook

Sheet Sheet1
C3: S.O. | D3: FY 15 | F3: FY 16 | H3: 43571 | I3: 43601 | J3: 43632 | K3: 43662 | L3: 43693 | M3: 43724 | N3: 43754 | O3: 43785 | P3: 43815 | Q3: 43846 | R3: 43877 | S3: 43906 | T3: Average | U3: Cumm.
D4: Month | E4: Cumm. | F4: Month | G4: Cumm | U4: =SUM(H4:S4) -> 0
B5: PNG | C5: 32120 | D5: =E5/12 -> 867188.58 | E5: 10406263 | F5: =G5/12 -> 507228.42 | G5: 6086741 | H5: 191277 | I5: 195721 | J5: 261627 | K5: 515014 | L5: 483750 | M5: 449127 | N5: 217770 | O5: 344894 | P5: 172014 | Q5: 253015 | R5: 443414 | T5: =AVERAGE(H5:S5) -> 320693 | U5: =SUM(H5:S5) -> 3527623
B6: Power | C6: 32016 | D6: =E6/12 -> 836059.5 | E6: 10032714 | F6: =G6/12 -> 794021.25 | G6: 9528255 | H6: 731507 | I6: 792791 | J6: 1020609 | K6: 1500634 | L6: 1174976 | M6: 1038601 | N6: 534169 | O6: 494113 | P6: 1025753 | Q6: 1385958 | R6: 1571598 | T6: =AVERAGE(H6:S6) -> 1024609.9 | U6: =SUM(H6:S6) -> 11270709
B7: HNP | C7: 32069 | D7: =E7/12 -> 402263.08 | E7: 4827157 | F7: =G7/12 -> 313321.17 | G7: 3759854 | H7: 158996 | I7: 193533 | J7: 146071 | K7: 292259 | L7: 263028 | M7: 302065 | N7: 230409 | O7: 198718 | P7: 146882 | Q7: 260124 | R7: 304537 | T7: =AVERAGE(H7:S7) -> 226965.64 | U7: =SUM(H7:S7) -> 2496622
B8: Water | C8: 32102 | D8: =E8/12 -> 86724.25 | E8: 1040691 | F8: =G8/12 -> 74871.25 | G8: 898455 | H8: 67888 | I8: 67312 | J8: 65773 | K8: 62119 | L8: 74047 | M8: 52531 | N8: 55635 | O8: 62289 | P8: 62814 | Q8: 69028 | R8: 79312 | T8: =AVERAGE(H8:S8) -> 65340.727 | U8: =SUM(H8:S8) -> 718748
B9: Acid | C9: 32103 | H9: 0 | I9: 37720 | J9: 0 | K9: 34980 | L9: 35765 | M9: 37260 | N9: 0 | O9: 37376 | P9: 0 | Q9: 0 | R9: 88921 | T9: =AVERAGE(H9:S9) -> 24729.273 | U9: =SUM(H9:S9) -> 272022
B10: Boiler Chemical | C10: 32104 | D10: =E10/12 -> 3607.0833 | E10: 43285 | F10: =G10/12 -> 13525.333 | G10: 162304 | H10: 0 | I10: 0 | J10: 0 | K10: 0 | L10: 0 | M10: 0 | N10: 0 | O10: 0 | P10: 0 | Q10: 0 | R10: 0 | T10: =AVERAGE(H10:S10) -> 0 | U10: =SUM(H10:S10) -> 0
B11: LIME | C11: 32105 | D11: =E11/12 -> 25955.583 | E11: 311467 | F11: =G11/12 -> 13525.333 | G11: 162304 | H11: 0 | I11: 0 | J11: 0 | K11: 33892 | L11: 34351 | M11: 0 | N11: 68701 | O11: 0 | P11: 0 | Q11: 0 | R11: 0 | T11: =AVERAGE(H11:S11) -> 12449.455 | U11: =SUM(H11:S11) -> 136944
B12: Chemicals | C12: 32106 | D12: =E12/12 -> 1444.1667 | E12: 17330 | F12: =G12/12 -> 4115 | G12: 49380 | H12: 127654 | I12: 80080 | J12: 56205 | K12: 111446 | L12: 112426 | M12: 109000 | N12: 114410 | O12: 34973 | P12: 210704 | Q12: 13320 | R12: 110000 | T12: =AVERAGE(H12:S12) -> 98201.636 | U12: =SUM(H12:S12) -> 1080218
B13: Reoiler Chemical | C13: 32107 | D13: =E13/12 -> 27498.917 | E13: 329987 | F13: =G13/12 -> 36697.917 | G13: 440375 | H13: 0 | I13: 0 | J13: 0 | K13: 0 | L13: 0 | M13: 0 | N13: 0 | O13: 0 | P13: 0 | Q13: 0 | R13: 0 | T13: =AVERAGE(H13:S13) -> 0 | U13: =SUM(H13:S13) -> 0
B14: Sludge dissposal | C14: 32108 | D14: =E14/12 -> 1681.1667 | E14: 20174 | F14: =G14/12 -> 1197.25 | G14: 14367 | H14: 0 | I14: 0 | J14: 0 | K14: 0 | L14: 0 | M14: 0 | N14: 0 | O14: 0 | P14: 0 | Q14: 0 | R14: 0 | T14: =AVERAGE(H14:S14) -> 0 | U14: =SUM(H14:S14) -> 0
B15: Water dissposal | C15: 32109 | H15: 0 | I15: 0 | J15: 0 | K15: 0 | L15: 0 | M15: 0 | N15: 0 | O15: 0 | P15: 0 | Q15: 0 | R15: 0 | T15: =AVERAGE(H15:S15) -> 0 | U15: =SUM(H15:S15) -> 0
B16: NTL Operting supply | C16: 32110 | D16: =E16/12 -> 745765.58 | E16: 8949187 | F16: =G16/12 -> 740206.92 | G16: 8882483 | H16: 1019070 | I16: 1983679 | J16: 300438 | K16: 270466 | L16: 319384 | M16: 169657 | N16: 166615 | O16: 255000 | P16: 18641 | Q16: 327393 | R16: 1001639 | T16: =AVERAGE(H16:S16) -> 530180.18 | U16: =SUM(H16:S16) -> 5831982
B17: NTL Miss | C17: 32111 | D17: =E17/12 -> 358969.75 | E17: 4307637 | F17: =G17/12 -> 273215.17 | G17: 3278582 | H17: 175787 | I17: 218300 | J17: 303780 | K17: 277427 | L17: 640977 | M17: 196780 | N17: 29507 | O17: 76826 | P17: 204102 | Q17: 83573 | R17: 108330 | T17: =AVERAGE(H17:S17) -> 210489.91 | U17: =SUM(H17:S17) -> 2315389
B18: R&M Flt 27 | C18: 32569 | D18: =E18/12 -> 3812.0833 | E18: 45745 | F18: =G18/12 -> 17892 | G18: 214704 | H18: 0 | I18: 0 | J18: 0 | K18: 6846 | L18: 0 | M18: 0 | N18: 0 | O18: 0 | P18: 0 | Q18: 0 | R18: 0 | T18: =AVERAGE(H18:S18) -> 622.36364 | U18: =SUM(H18:S18) -> 6846
B19: Wage | C19: 32141 | D19: =E19/12 -> 890381.58 | E19: 10684579 | F19: =G19/12 -> 957392 | G19: 11488704 | H19: 1107770 | I19: 1219812 | J19: 1145879 | K19: 1121937 | L19: 1225712 | M19: 1167862 | N19: 1203699 | O19: 1163296 | P19: 1104126 | Q19: 1474469 | R19: 1241859 | T19: =AVERAGE(H19:S19) -> 1197856.5 | U19: =SUM(H19:S19) -> 13176421
B20: OT | C20: 32049 | D20: =E20/12 -> 161374.67 | E20: 1936496 | F20: =G20/12 -> 169641.17 | G20: 2035694 | H20: 124471 | I20: 166720 | J20: 150077 | K20: 177415 | L20: 130564 | M20: 212443 | N20: 134695 | O20: 191305 | P20: 165967 | Q20: 186513 | R20: 234587 | T20: =AVERAGE(H20:S20) -> 170432.45 | U20: =SUM(H20:S20) -> 1874757
B21: Boiler RnM Eletrical | C21: 32401 | D21: =E21/12 -> 1516.1667 | E21: 18194 | F21: =G21/12 -> 5868.25 | G21: 70419 | H21: 0 | I21: 0 | J21: 0 | K21: 0 | L21: 0 | M21: 0 | N21: 0 | O21: 0 | P21: 0 | Q21: 0 | R21: 0 | T21: =AVERAGE(H21:S21) -> 0 | U21: =SUM(H21:S21) -> 0
B22: ETP RnM Eletrical | C22: 32402 | D22: =E22/12 -> 3632.25 | E22: 43587 | F22: =G22/12 -> 7425.0833 | G22: 89101 | H22: 195 | I22: 0 | J22: 0 | K22: 0 | L22: 0 | M22: 0 | N22: 0 | O22: 0 | P22: 0 | Q22: 2711 | R22: 0 | T22: =AVERAGE(H22:S22) -> 264.18182 | U22: =SUM(H22:S22) -> 2906
B23: Lighting RnM Eletrical | C23: 32403 | D23: =E23/12 -> 486.83333 | E23: 5842 | F23: =G23/12 -> 126.16667 | G23: 1514 | H23: 0 | I23: 0 | J23: 0 | K23: 0 | L23: 0 | M23: 0 | N23: 0 | O23: 0 | P23: 0 | Q23: 1317 | R23: 0 | T23: =AVERAGE(H23:S23) -> 119.72727 | U23: =SUM(H23:S23) -> 1317
B24: Transformer RnM Eletrical | C24: 32404 | D24: =E24/12 -> 3133.8333 | E24: 37606 | F24: =G24/12 -> 0 | G24: 0 | H24: 0 | I24: 0 | J24: 0 | K24: 0 | L24: 0 | M24: 0 | N24: 0 | O24: 0 | P24: 0 | Q24: 0 | R24: 0 | T24: =AVERAGE(H24:S24) -> 0 | U24: =SUM(H24:S24) -> 0
B25: Ventilation RnM Eletrical | C25: 32405 | D25: =E25/12 -> 679.91667 | E25: 8159 | F25: =G25/12 -> 0 | G25: 0 | H25: 0 | I25: 0 | J25: 0 | K25: 0 | L25: 0 | M25: 0 | N25: 0 | O25: 0 | P25: 0 | Q25: 0 | R25: 0 | T25: =AVERAGE(H25:S25) -> 0 | U25: =SUM(H25:S25) -> 0
B26: NTL RnM Eletrical | C26: 32413 | D26: =E26/12 -> 57416.25 | E26: 688995 | F26: =G26/12 -> 321699.5 | G26: 3860394 | H26: 7756 | I26: 80285 | J26: 46996 | K26: 94954 | L26: 22309 | M26: 46288 | N26: 20358 | O26: 84506 | P26: 52721 | Q26: 1403 | R26: 10762 | T26: =AVERAGE(H26:S26) -> 42576.182 | U26: =SUM(H26:S26) -> 468338
B27: Motors RnM Eletrical | C27: 32414 | D27: =E27/12 -> 3920.0833 | E27: 47041 | F27: =G27/12 -> 3235.4167 | G27: 38825 | H27: 0 | I27: 0 | J27: 0 | K27: 0 | L27: 0 | M27: 0 | N27: 0 | O27: 0 | P27: 16415 | Q27: 8649 | R27: 12123 | T27: =AVERAGE(H27:S27) -> 3380.6364 | U27: =SUM(H27:S27) -> 37187
... B37: EOT RnM Mechnical | C37: 32484 | D37: =E37/12 -> 3948.9167 | E37: 47387 | F37: =G37/12 -> 5375.8333 | G37: 64510 | H37: 0 | I37: 0 | J37: 0 | K37: 0 | L37: 0 | M37: 0 | N37: 0 | O37: 0 | P37: 0 | Q37: 0 | R37: 0 | T37: =AVERAGE(H37:S37) -> 0 | U37: =SUM(H37:S37) -> 0
B38: Disele for FLT 27 (17) | C38: 32766 | H38: 12747 | I38: 11237 | J38: 10800 | K38: 70333 | L38: 18396 | M38: 15807 | N38: 12987 | O38: 13905 | P38: 19302 | Q38: 22538 | R38: 24419 | T38: =AVERAGE(H38:S38) -> 21133.727 | U38: =SUM(H38:S38) -> 232471

Sheet Sheet2
B1: 43556 | C1: 43586 | D1: 43617 | E1: 43647 | F1: 43678 | G1: 43709 | H1: 43739 | I1: 43770 | J1: 43800 | K1: 43831 | L1: 43862 | M1: 43891 | N1: YTD FY 19 | O1: Ytd avg
A3: TL Production | B3: 365 | C3: 420 | D3: 635 | E3: 1052 | F3: 677 | G3: 860 | H3: 640 | I3: 862 | J3: 762 | K3: 760 | L3: 977 | N3: =SUM(B3:M3) -> 8010 | O3: =AVERAGE(B3:M3) -> 728.18182
B5: Rs. | C5: Rs. | D5: Rs. | E5: Rs. | F5: Rs. | G5: Rs. | H5: Rs. | I5: Rs. | J5: Rs. | K5: Rs. | L5: Rs. | M5: Rs. | N5: Rs. | O5: Rs.
A6: Operating Supplies | B6: =SUM(Sheet1!H7:H17,Sheet1!H38) -> 1562142 | C6: =SUM(Sheet1!I7:I17,Sheet1!I38) -> 2591861 | D6: =SUM(Sheet1!J7:J17,Sheet1!J38) -> 883067 | E6: =SUM(Sheet1!K7:K17,Sheet1!K38) -> 1152922 | F6: =SUM(Sheet1!L7:L17,Sheet1!L38) -> 1498374 | G6: =SUM(Sheet1!M7:M17,Sheet1!M38) -> 883100 | H6: =SUM(Sheet1!N7:N17,Sheet1!N38) -> 678264 | I6: =SUM(Sheet1!O7:O17,Sheet1!O38) -> 679087 | ... L6: =SUM(Sheet1!R7:R17,Sheet1!R38) -> 1717158 | N6: =SUM(B6:M6) -> 13084396 | O6: =AVERAGE(B6:M6) -> 1189490.5
A7: Power | B7: =Sheet1!H6 -> 731507 | C7: =Sheet1!I6 -> 792791 | D7: =Sheet1!J6 -> 1020609 | E7: =Sheet1!K6 -> 1500634 | F7: =Sheet1!L6 -> 1174976 | G7: =Sheet1!M6 -> 1038601 | H7: =Sheet1!N6 -> 534169 | I7: =Sheet1!O6 -> 494113 | ... L7: =Sheet1!R6 -> 1571598 | N7: =SUM(B7:M7) -> 11270709 | O7: =AVERAGE(B7:M7) -> 1024609.9
A8: Gas | B8: =Sheet1!H5 -> 191277 | C8: =Sheet1!I5 -> 195721 | D8: =Sheet1!J5 -> 261627 | E8: =Sheet1!K5 -> 515014 | F8: =Sheet1!L5 -> 483750 | G8: =Sheet1!M5 -> 449127 | H8: =Sheet1!N5 -> 217770 | I8: =Sheet1!O5 -> 344894 | ... L8: =Sheet1!R5 -> 443414 | N8: =SUM(B8:M8) -> 3527623 | O8: =AVERAGE(B8:M8) -> 320693
B9: =B6/B3 -> 4279.8411 | C9: =C6/C3 -> 6171.0976 | D9: =D6/D3 -> 1390.6567 | E9: =E6/E3 -> 1095.9335 | F9: =F6/F3 -> 2213.2555 | G9: =G6/G3 -> 1026.8605 | H9: =H6/H3 -> 1059.7875 | I9: =I6/I3 -> 787.80394 | ... L9: =L6/L3 -> 1757.5824 | N9: =SUM(B9:M9) -> 21673.19 | O9: =AVERAGE(B9:M9) -> 1970.29
A10: TOTAL VARIABLE COST | B10: =SUM(B6:B8) -> 2484926 | C10: =SUM(C6:C8) -> 3580373 | D10: =SUM(D6:D8) -> 2165303 | E10: =SUM(E6:E8) -> 3168570 | F10: =SUM(F6:F8) -> 3157100 | G10: =SUM(G6:G8) -> 2370828 | H10: =SUM(H6:H8) -> 1430203 | I10: =SUM(I6:I8) -> 1518094 | ... L10: =SUM(L6:L8) -> 3732170 | N10: =SUM(N6:N9) -> 27904401 | O10: =SUM(O6:O9) -> 2536763.7
A12: Employment Cost | B12: =SUM(Sheet1!H19:H20) -> 1232241 | C12: =SUM(Sheet1!I19:I20) -> 1386532 | D12: =SUM(Sheet1!J19:J20) -> 1295956 | E12: =SUM(Sheet1!K19:K20) -> 1299352 | F12: =SUM(Sheet1!L19:L20) -> 1356276 | G12: =SUM(Sheet1!M19:M20) -> 1380305 | H12: =SUM(Sheet1!N19:N20) -> 1338394 | I12: =SUM(Sheet1!O19:O20) -> 1354601 | ... L12: =SUM(Sheet1!R19:R20) -> 1476446 | N12: =SUM(B12:M12) -> 15051178 | O12: =AVERAGE(B12:M12) -> 1368288.9
A13: R&M | B13: =SUM(Sheet1!H21:H37) -> 127378 | C13: =SUM(Sheet1!I21:I37) -> 219735 | D13: =SUM(Sheet1!J21:J37) -> 66016 | E13: =SUM(Sheet1!K21:K37) -> 275070 | F13: =SUM(Sheet1!L21:L37) -> 213389 | G13: =SUM(Sheet1!M21:M37) -> 177059 | H13: =SUM(Sheet1!N21:N37) -> 626610 | I13: =SUM(Sheet1!O21:O37) -> 230675 | ... L13: =SUM(Sheet1!R21:R37) -> 272520 | N13: =SUM(B13:M13) -> 2608631 | O13: =AVERAGE(B13:M13) -> 237148.27
A14: Others | N14: =SUM(B14:M14) -> 0 | O14: =AVERAGE(B14:M14) -> #DIV/0!
A15: TOTAL FIXED COST | B15: =B12+B13 -> 1359619 | C15: =C12+C13 -> 1606267 | D15: =D12+D13 -> 1361972 | E15: =E12+E13 -> 1574422 | F15: =F12+F13 -> 1569665 | G15: =G12+G13 -> 1557364 | H15: =H12+H13 -> 1965004 | I15: =I12+I13 -> 1585276 | ... L15: =L12+L13 -> 1748966 | N15: =SUM(N12:N14) -> 17659809 | O15: =SUM(O12:O14) -> #DIV/0!
A17: Depreciation | N17: =SUM(B17:M17) -> 0 | O17: =AVERAGE(B17:M17) -> #DIV/0!
A19: Total Expenses | B19: =B15+B10 -> 3844545 | C19: =C15+C10 -> 5186640 | D19: =D15+D10 -> 3527275 | E19: =E15+E10 -> 4742992 | F19: =F15+F10 -> 4726765 | G19: =G15+G10 -> 3928192 | H19: =H15+H10 -> 3395207 | I19: =I15+I10 -> 3103370 | ... L19: =L15+L10 -> 5481136 | N19: =+N10+N15+N17 -> 45564210 | O19: =+O10+O15+O17 -> #DIV/0!
A21: Less Abnormal Exp | N21: =SUM(B21:M21) -> 0 | O21: =AVERAGE(B21:M21) -> #DIV/0!
A24: Normal Expenses | N24: =+N19-N21 -> 45564210 | O24: =+O19-O21 -> #DIV/0!
A27: Total Expenses | B27: =B19 -> 3844545 | C27: =C19 -> 5186640 | D27: =D19 -> 3527275 | E27: =E19 -> 4742992 | F27: =F19 -> 4726765 | G27: =G19 -> 3928192 | H27: =H19 -> 3395207 | I27: =I19 -> 3103370 | ... L27: =L19 -> 5481136 | N27: =SUM(B27:M27) -> 45542537 | O27: =AVERAGE(B27:M27) -> 4140230.6
A29: Rs/T With Freight | B29: =(B27/B3) -> 10533 | C29: =(C27/C3) -> 12349.143 | D29: =(D27/D3) -> 5554.7638 | E29: =(E27/E3) -> 4508.5475 | F29: =(F27/F3) -> 6981.9276 | G29: =(G27/G3) -> 4567.6651 | H29: =(H27/H3) -> 5305.0109 | I29: =(I27/I3) -> 3600.1972 | ... M29: =(M27/M3) -> #DIV/0! | N29: =ROUND(+N27/N3,0) -> 5686 | O29: =ROUND(+O27/O3,0) -> 5686

Sheet Sheet3
